wagtailmakeup/__init__.py
wagtailmakeup/api.py
wagtailmakeup/settings.py
wagtailmakeup/management/__init__.py
wagtailmakeup/management/commands/__init__.py
wagtailmakeup/management/commands/make_up.py
wagtailmakeup/migrations/__init__.py
wagtailmakeup/tests/__init__.py
wagtailmakeup/tests/settings.py
wagtailmakeup/tests/tests.py
wagtailmakeup/tests/urls.py
wagtailmakeup-1.1.0.dist-info/METADATA
wagtailmakeup-1.1.0.dist-info/WHEEL
wagtailmakeup-1.1.0.dist-info/top_level.txt
wagtailmakeup-1.1.0.dist-info/RECORD
