Metadata-Version: 2.1
Name: wagtailmakeup
Version: 1.1.0
Summary: Wagtail Makeup
Home-page: https://github.com/kevinhowbrook/wagtail-makeup
Author: Kevin Howbrook
License: MIT
Keywords: wagtail,django
Classifier: Development Status :: 3 - Alpha
Classifier: Environment :: Web Environment
Classifier: Framework :: Django
Classifier: Framework :: Django :: 3.2
Classifier: Framework :: Django :: 4.2
Classifier: Framework :: Django :: 5.0
Classifier: Framework :: Wagtail
Classifier: Framework :: Wagtail :: 5
Classifier: Framework :: Wagtail :: 6
Requires-Python: >=3.8
Requires-Dist: wagtail >=5.2
Requires-Dist: python-unsplash >=1.1.0
Provides-Extra: testing
Requires-Dist: coverage >=4.5 ; extra == 'testing'
